{
  "quote": "Asleep, he looked a lot younger than going-on-seventeen, but I had noticed that Johnny looked younger when he was asleep too, so I figured everyone did. Maybe people are younger when they are asleep.",
  "quote_letters": "ASLEEP HE LOOKED A LOT YOUNGER THAN GOING-ON-SEVENTEEN BUT I HAD NOTICED THAT JOHNNY LOOKED YOUNGER WHEN HE WAS ASLEEP TOO SO I FIGURED EVERYONE DID MAYBE PEOPLE ARE YOUNGER WHEN THEY ARE ASLEEP",
  "source": "S.E. Hinton, The Outsiders",
  "source_letters": "SEHINTONTHEOUTSIDERS",
  "clues": [
    {
      "clue": null,
      "answer": "sleeve",
      "answer_letters": "SLEEVE",
      "indices": [
        45,
        2,
        4,
        133,
        137,
        8
      ]
    },
    {
      "clue": null,
      "answer": "eleanor",
      "answer_letters": "ELEANOR",
      "indices": [
        186,
        85,
        171,
        184,
        43,
        79,
        132
      ]
    },
    {
      "clue": null,
      "answer": "hypotheses",
      "answer_letters": "HYPOTHESES",
      "indices": [
        175,
        92,
        193,
        86,
        57,
        7,
        153,
        1,
        48,
        123
      ]
    },
    {
      "clue": null,
      "answer": "intermediate",
      "answer_letters": "INTERMEDIATE",
      "indices": [
        38,
        34,
        21,
        160,
        98,
        149,
        51,
        134,
        126,
        109,
        119,
        176
      ]
    },
    {
      "clue": null,
      "answer": "nephew",
      "answer_letters": "NEPHEW",
      "indices": [
        81,
        89,
        158,
        61,
        192,
        174
      ]
    },
    {
      "clue": null,
      "answer": "typhoon",
      "answer_letters": "TYPHOON",
      "indices": [
        179,
        83,
        155,
        80,
        87,
        12,
        177
      ]
    },
    {
      "clue": null,
      "answer": "overlooking",
      "answer_letters": "OVERLOOKING",
      "indices": [
        124,
        47,
        52,
        139,
        19,
        42,
        141,
        13,
        59,
        53,
        96
      ]
    },
    {
      "clue": null,
      "answer": "non-league",
      "answer_letters": "NONLEAGUE",
      "indices": [
        103,
        121,
        142,
        10,
        46,
        150,
        40,
        168,
        136
      ]
    },
    {
      "clue": null,
      "answer": "though",
      "answer_letters": "THOUGH",
      "indices": [
        50,
        105,
        11,
        56,
        27,
        32
      ]
    },
    {
      "clue": null,
      "answer": "hollywood",
      "answer_letters": "HOLLYWOOD",
      "indices": [
        180,
        24,
        159,
        114,
        23,
        100,
        37,
        167,
        15
      ]
    },
    {
      "clue": null,
      "answer": "engage",
      "answer_letters": "ENGAGE",
      "indices": [
        28,
        39,
        130,
        162,
        36,
        3
      ]
    },
    {
      "clue": null,
      "answer": "one-year",
      "answer_letters": "ONEYEAR",
      "indices": [
        66,
        65,
        97,
        182,
        115,
        17,
        185
      ]
    },
    {
      "clue": null,
      "answer": "underground",
      "answer_letters": "UNDERGROUND",
      "indices": [
        25,
        26,
        90,
        143,
        172,
        170,
        29,
        157,
        131,
        49,
        63
      ]
    },
    {
      "clue": null,
      "answer": "topeka",
      "answer_letters": "TOPEKA",
      "indices": [
        31,
        93,
        5,
        164,
        88,
        0
      ]
    },
    {
      "clue": null,
      "answer": "speedy",
      "answer_letters": "SPEEDY",
      "indices": [
        113,
        117,
        156,
        191,
        145,
        166
      ]
    },
    {
      "clue": null,
      "answer": "inhabited",
      "answer_letters": "INHABITED",
      "indices": [
        68,
        82,
        74,
        33,
        55,
        146,
        76,
        116,
        147
      ]
    },
    {
      "clue": null,
      "answer": "define",
      "answer_letters": "DEFINE",
      "indices": [
        71,
        181,
        128,
        129,
        95,
        106
      ]
    },
    {
      "clue": null,
      "answer": "enjoyable",
      "answer_letters": "ENJOYABLE",
      "indices": [
        14,
        169,
        78,
        120,
        140,
        112,
        152,
        190,
        138
      ]
    },
    {
      "clue": null,
      "answer": "raceway",
      "answer_letters": "RACEWAY",
      "indices": [
        163,
        188,
        69,
        70,
        108,
        62,
        151
      ]
    },
    {
      "clue": null,
      "answer": "southeast",
      "answer_letters": "SOUTHEAST",
      "indices": [
        189,
        20,
        94,
        67,
        101,
        102,
        75,
        110,
        73
      ]
    }
  ],
  "chat": null
}