{
  "quote": "Today there could be laughter and freedom, but soon the magic would end and they would have to go back to the real world. However, there would still always be time to get under Dak's skin.",
  "quote_letters": "TODAY THERE COULD BE LAUGHTER AND FREEDOM BUT SOON THE MAGIC WOULD END AND THEY WOULD HAVE TO GO BACK TO THE REAL WORLD HOWEVER THERE WOULD STILL ALWAYS BE TIME TO GET UNDER DAKS SKIN",
  "source": "Alyson Serena Stone, Once",
  "source_letters": "ALYSONSERENASTONEONCE",
  "clues": [
    {
      "clue": null,
      "answer": "attacked",
      "answer_letters": "ATTACKED",
      "indices": [
        149,
        0,
        44,
        175,
        59,
        100,
        19,
        174
      ]
    },
    {
      "clue": null,
      "answer": "lehigh",
      "answer_letters": "LEHIGH",
      "indices": [
        21,
        110,
        7,
        58,
        24,
        106
      ]
    },
    {
      "clue": null,
      "answer": "youngest",
      "answer_letters": "YOUNGEST",
      "indices": [
        150,
        103,
        63,
        72,
        164,
        67,
        151,
        166
      ]
    },
    {
      "clue": null,
      "answer": "subtle",
      "answer_letters": "SUBTLE",
      "indices": [
        140,
        43,
        153,
        75,
        147,
        132
      ]
    },
    {
      "clue": null,
      "answer": "oldham",
      "answer_letters": "OLDHAM",
      "indices": [
        39,
        143,
        170,
        129,
        71,
        40
      ]
    },
    {
      "clue": null,
      "answer": "notified",
      "answer_letters": "NOTIFIED",
      "indices": [
        169,
        48,
        26,
        142,
        34,
        157,
        159,
        118
      ]
    },
    {
      "clue": null,
      "answer": "skulls",
      "answer_letters": "SKULLS",
      "indices": [
        46,
        176,
        168,
        117,
        83,
        177
      ]
    },
    {
      "clue": null,
      "answer": "evolved",
      "answer_letters": "EVOLVED",
      "indices": [
        123,
        124,
        121,
        112,
        88,
        165,
        32
      ]
    },
    {
      "clue": null,
      "answer": "re-elected",
      "answer_letters": "REELECTED",
      "indices": [
        9,
        27,
        8,
        15,
        130,
        12,
        105,
        77,
        2
      ]
    },
    {
      "clue": null,
      "answer": "erebidae",
      "answer_letters": "EREBIDAE",
      "indices": [
        154,
        28,
        10,
        97,
        181,
        84,
        87,
        107
      ]
    },
    {
      "clue": null,
      "answer": "norway",
      "answer_letters": "NORWAY",
      "indices": [
        49,
        13,
        35,
        61,
        22,
        4
      ]
    },
    {
      "clue": null,
      "answer": "allotted",
      "answer_letters": "ALLOTTED",
      "indices": [
        3,
        144,
        64,
        1,
        128,
        161,
        125,
        73
      ]
    },
    {
      "clue": null,
      "answer": "sabbath",
      "answer_letters": "SABBATH",
      "indices": [
        179,
        30,
        18,
        42,
        98,
        91,
        25
      ]
    },
    {
      "clue": null,
      "answer": "through",
      "answer_letters": "THROUGH",
      "indices": [
        51,
        120,
        116,
        115,
        14,
        57,
        86
      ]
    },
    {
      "clue": null,
      "answer": "ottawa",
      "answer_letters": "OTTAWA",
      "indices": [
        95,
        156,
        102,
        111,
        80,
        146
      ]
    },
    {
      "clue": null,
      "answer": "norwood",
      "answer_letters": "NORWOOD",
      "indices": [
        182,
        62,
        131,
        122,
        47,
        135,
        38
      ]
    },
    {
      "clue": null,
      "answer": "emerged",
      "answer_letters": "EMERGED",
      "indices": [
        171,
        158,
        89,
        126,
        94,
        36,
        69
      ]
    },
    {
      "clue": null,
      "answer": "outlaw",
      "answer_letters": "OUTLAW",
      "indices": [
        162,
        136,
        6,
        137,
        56,
        148
      ]
    },
    {
      "clue": null,
      "answer": "network",
      "answer_letters": "NETWORK",
      "indices": [
        68,
        37,
        141,
        134,
        81,
        109,
        180
      ]
    },
    {
      "clue": null,
      "answer": "chowdhury",
      "answer_letters": "CHOWDHURY",
      "indices": [
        99,
        76,
        92,
        114,
        138,
        52,
        23,
        172,
        78
      ]
    },
    {
      "clue": null,
      "answer": "edmund",
      "answer_letters": "EDMUND",
      "indices": [
        53,
        16,
        55,
        82,
        31,
        65
      ]
    }
  ],
  "chat": null
}