{
  "quote": "I could smack her, punch her in the face, but then I see what she can't hide from me. I've seen it before-the desperation, the agony, the need to find a reason to go on, and the inability to find it.",
  "quote_letters": "I COULD SMACK HER PUNCH HER IN THE FACE BUT THEN I SEE WHAT SHE CANT HIDE FROM ME IVE SEEN IT BEFORE-THE DESPERATION THE AGONY THE NEED TO FIND A REASON TO GO ON AND THE INABILITY TO FIND IT",
  "source": "Mary Beth Miller, Aimee",
  "source_letters": "MARYBETHMILLERAIMEE",
  "clues": [
    {
      "clue": "Twelve slices of time.",
      "answer": "months",
      "answer_letters": "MONTHS",
      "indices": [
        77,
        159,
        131,
        101,
        61,
        8
      ]
    },
    {
      "clue": "Tender regard for someone.",
      "answer": "affection",
      "answer_letters": "AFFECTION",
      "indices": [
        144,
        74,
        35,
        46,
        11,
        117,
        70,
        114,
        163
      ]
    },
    {
      "clue": "Allowed entry again following an earlier closure.",
      "answer": "reopened",
      "answer_letters": "REOPENED",
      "indices": [
        110,
        15,
        137,
        108,
        88,
        171,
        33,
        71
      ]
    },
    {
      "clue": "Teens or adolescents.",
      "answer": "youths",
      "answer_letters": "YOUTHS",
      "indices": [
        178,
        123,
        41,
        44,
        14,
        60
      ]
    },
    {
      "clue": "Verb describing what happens to a guillotined person.",
      "answer": "beheaded",
      "answer_letters": "BEHEADED",
      "indices": [
        94,
        168,
        69,
        84,
        148,
        142,
        62,
        164
      ]
    },
    {
      "clue": "A protocol suite used for LANs.",
      "answer": "ethernet",
      "answer_letters": "ETHERNET",
      "indices": [
        133,
        189,
        32,
        109,
        26,
        29,
        95,
        153
      ]
    },
    {
      "clue": "Hence or consequently",
      "answer": "therefore",
      "answer_letters": "THEREFORE",
      "indices": [
        112,
        45,
        132,
        16,
        103,
        139,
        181,
        75,
        53
      ]
    },
    {
      "clue": "Opposite of 'coldest' in terms of temperature.",
      "answer": "hottest",
      "answer_letters": "HOTTEST",
      "indices": [
        118,
        97,
        166,
        42,
        52,
        149,
        92
      ]
    },
    {
      "clue": "First workday for most.",
      "answer": "mondays",
      "answer_letters": "MONDAYS",
      "indices": [
        79,
        76,
        141,
        6,
        10,
        125,
        86
      ]
    },
    {
      "clue": "Once included Vietnam, Laos, and Cambodia.",
      "answer": "indochina",
      "answer_letters": "INDOCHINA",
      "indices": [
        49,
        160,
        105,
        3,
        37,
        56,
        184,
        89,
        162
      ]
    },
    {
      "clue": "A school that once featured a football rivalry with Lafayette College.",
      "answer": "lehigh",
      "answer_letters": "LEHIGH",
      "indices": [
        5,
        147,
        128,
        82,
        122,
        102
      ]
    },
    {
      "clue": "Scottish painter famous for his work in the Victorian era.",
      "answer": "leighton",
      "answer_letters": "LEIGHTON",
      "indices": [
        175,
        106,
        174,
        156,
        167,
        58,
        157,
        47
      ]
    },
    {
      "clue": "Optimal in performance or productivity.",
      "answer": "efficient",
      "answer_letters": "EFFICIENT",
      "indices": [
        80,
        96,
        183,
        170,
        64,
        176,
        129,
        185,
        177
      ]
    },
    {
      "clue": "An arc in the sky following a storm.",
      "answer": "rainbow",
      "answer_letters": "RAINBOW",
      "indices": [
        98,
        65,
        0,
        151,
        40,
        150,
        55
      ]
    },
    {
      "clue": "Made operational",
      "answer": "activated",
      "answer_letters": "ACTIVATED",
      "indices": [
        111,
        2,
        180,
        91,
        83,
        172,
        31,
        72,
        134
      ]
    },
    {
      "clue": "Admission to school is known as an _.",
      "answer": "intake",
      "answer_letters": "INTAKE",
      "indices": [
        28,
        115,
        67,
        57,
        12,
        99
      ]
    },
    {
      "clue": "Japanese automotive giant.",
      "answer": "mitsubishi",
      "answer_letters": "MITSUBISHI",
      "indices": [
        9,
        140,
        136,
        107,
        19,
        173,
        113,
        51,
        22,
        188
      ]
    },
    {
      "clue": "Cursed with love's spells (in older usage).",
      "answer": "enchanted",
      "answer_letters": "ENCHANTED",
      "indices": [
        119,
        66,
        21,
        24,
        121,
        124,
        127,
        87,
        186
      ]
    },
    {
      "clue": "From a continent known for its classical music and art.",
      "answer": "european",
      "answer_letters": "EUROPEAN",
      "indices": [
        25,
        4,
        146,
        154,
        18,
        38,
        36,
        20
      ]
    }
  ],
  "chat": null
}