{
  "quote": "It was impossible to get the Dimitri and Tasha thing out of my head, but at least packing and getting ready made sure I didn't devote 100 percent of my brain power to him. More like 95 percent.",
  "quote_letters": "IT WAS IMPOSSIBLE TO GET THE DIMITRI AND TASHA THING OUT OF MY HEAD BUT AT LEAST PACKING AND GETTING READY MADE SURE I DIDNT DEVOTE  PERCENT OF MY BRAIN POWER TO HIM MORE LIKE  PERCENT",
  "source": "Richelle Mead, Frostbite",
  "source_letters": "RICHELLEMEADFROSTBITE",
  "clues": [
    {
      "clue": "A consistent beat in music.",
      "answer": "rhythm",
      "answer_letters": "RHYTHM",
      "indices": [
        179,
        63,
        61,
        79,
        44,
        8
      ]
    },
    {
      "clue": "A segment of a baseball game.",
      "answer": "inning",
      "answer_letters": "INNING",
      "indices": [
        49,
        151,
        50,
        85,
        122,
        93
      ]
    },
    {
      "clue": "Engaged in a contest or challenge.",
      "answer": "competed",
      "answer_letters": "COMPETED",
      "indices": [
        136,
        57,
        31,
        81,
        156,
        1,
        130,
        66
      ]
    },
    {
      "clue": "An organism resulting from the fusion of two different species.",
      "answer": "hybrid",
      "answer_letters": "HYBRID",
      "indices": [
        26,
        105,
        14,
        114,
        35,
        125
      ]
    },
    {
      "clue": "A geographic direction.",
      "answer": "east-west",
      "answer_letters": "EASTWEST",
      "indices": [
        115,
        72,
        78,
        96,
        155,
        22,
        12,
        33
      ]
    },
    {
      "clue": "A Greek letter often used in mathematical notations.",
      "answer": "lambda",
      "answer_letters": "LAMBDA",
      "indices": [
        15,
        4,
        107,
        147,
        91,
        89
      ]
    },
    {
      "clue": "A five-line nonsense poem.",
      "answer": "limerick",
      "answer_letters": "LIMERICK",
      "indices": [
        75,
        13,
        144,
        27,
        101,
        172,
        83,
        84
      ]
    },
    {
      "clue": "Made changes to a document.",
      "answer": "edited",
      "answer_letters": "EDITED",
      "indices": [
        137,
        121,
        30,
        55,
        126,
        104
      ]
    },
    {
      "clue": "Australian pop star with the given name Kylie.",
      "answer": "minogue",
      "answer_letters": "MINOGUE",
      "indices": [
        164,
        120,
        90,
        19,
        51,
        54,
        169
      ]
    },
    {
      "clue": "Made changes to a document.",
      "answer": "edited",
      "answer_letters": "EDITED",
      "indices": [
        110,
        29,
        32,
        139,
        181,
        119
      ]
    },
    {
      "clue": "Sensory organs atop insects' heads.",
      "answer": "antennae",
      "answer_letters": "ANTENNAE",
      "indices": [
        149,
        138,
        95,
        76,
        98,
        86,
        45,
        178
      ]
    },
    {
      "clue": "To lose a battle or contest.",
      "answer": "defeat",
      "answer_letters": "DEFEAT",
      "indices": [
        109,
        134,
        142,
        102,
        103,
        47
      ]
    },
    {
      "clue": "Scottish surname.",
      "answer": "forsyth",
      "answer_letters": "FORSYTH",
      "indices": [
        58,
        160,
        168,
        5,
        145,
        123,
        162
      ]
    },
    {
      "clue": "Characterized by regular recurrence.",
      "answer": "repetitive",
      "answer_letters": "REPETITIVE",
      "indices": [
        148,
        16,
        133,
        94,
        73,
        97,
        41,
        117,
        127,
        64
      ]
    },
    {
      "clue": "Choosing a preference.",
      "answer": "opting",
      "answer_letters": "OPTING",
      "indices": [
        10,
        9,
        129,
        0,
        182,
        99
      ]
    },
    {
      "clue": "A Malaysian state on the island of Borneo.",
      "answer": "sarawak",
      "answer_letters": "SARAWAK",
      "indices": [
        112,
        65,
        34,
        37,
        3,
        42,
        173
      ]
    },
    {
      "clue": "A red fruit used in salads and sauces.",
      "answer": "tomato",
      "answer_letters": "TOMATO",
      "indices": [
        18,
        128,
        60,
        82,
        70,
        167
      ]
    },
    {
      "clue": "Delivered something to a place.",
      "answer": "brought",
      "answer_letters": "BROUGHT",
      "indices": [
        68,
        157,
        53,
        69,
        87,
        48,
        23
      ]
    },
    {
      "clue": "A follower of a certain political movement.",
      "answer": "islamist",
      "answer_letters": "ISLAMIST",
      "indices": [
        163,
        43,
        171,
        77,
        166,
        150,
        11,
        25
      ]
    },
    {
      "clue": "A flavor enhancer placed on food.",
      "answer": "topping",
      "answer_letters": "TOPPING",
      "indices": [
        183,
        154,
        177,
        153,
        7,
        38,
        21
      ]
    },
    {
      "clue": "Someone who teaches.",
      "answer": "educator",
      "answer_letters": "EDUCATOR",
      "indices": [
        174,
        39,
        113,
        180,
        108,
        159,
        141,
        135
      ]
    }
  ],
  "chat": null
}