{
  "quote": "I am a runner. Not an actual runner, like with shoes and sweat. Instead, I specialize in leaving uncomfortable situations with alarming speed. Some people need closure, I need space.",
  "quote_letters": "I AM A RUNNER NOT AN ACTUAL RUNNER LIKE WITH SHOES AND SWEAT INSTEAD I SPECIALIZE IN LEAVING UNCOMFORTABLE SITUATIONS WITH ALARMING SPEED SOME PEOPLE NEED CLOSURE I NEED SPACE",
  "source": "Emma Nichols, Sin at Sea",
  "source_letters": "EMMANICHOLSSINATSEA",
  "clues": [
    {
      "clue": null,
      "answer": "erebidae",
      "answer_letters": "EREBIDAE",
      "indices": [
        38,
        160,
        166,
        103,
        128,
        67,
        125,
        73
      ]
    },
    {
      "clue": null,
      "answer": "monastic",
      "answer_letters": "MONASTIC",
      "indices": [
        3,
        157,
        83,
        2,
        116,
        64,
        61,
        95
      ]
    },
    {
      "clue": null,
      "answer": "monitored",
      "answer_letters": "MONITORED",
      "indices": [
        97,
        114,
        14,
        41,
        59,
        15,
        28,
        135,
        153
      ]
    },
    {
      "clue": null,
      "answer": "appear",
      "answer_letters": "APPEAR",
      "indices": [
        87,
        171,
        143,
        86,
        25,
        12
      ]
    },
    {
      "clue": null,
      "answer": "nemesis",
      "answer_letters": "NEMESIS",
      "indices": [
        52,
        167,
        127,
        144,
        55,
        89,
        138
      ]
    },
    {
      "clue": null,
      "answer": "issuing",
      "answer_letters": "ISSUING",
      "indices": [
        69,
        45,
        71,
        24,
        108,
        10,
        130
      ]
    },
    {
      "clue": null,
      "answer": "coalition",
      "answer_letters": "COALITION",
      "indices": [
        173,
        99,
        123,
        104,
        82,
        16,
        75,
        47,
        62
      ]
    },
    {
      "clue": null,
      "answer": "helpful",
      "answer_letters": "HELPFUL",
      "indices": [
        121,
        134,
        85,
        133,
        98,
        159,
        77
      ]
    },
    {
      "clue": null,
      "answer": "outlawed",
      "answer_letters": "OUTLAWED",
      "indices": [
        96,
        29,
        109,
        147,
        51,
        56,
        174,
        136
      ]
    },
    {
      "clue": null,
      "answer": "leuven",
      "answer_letters": "LEUVEN",
      "indices": [
        35,
        32,
        110,
        88,
        148,
        165
      ]
    },
    {
      "clue": null,
      "answer": "science",
      "answer_letters": "SCIENCE",
      "indices": [
        63,
        22,
        0,
        151,
        30,
        74,
        57
      ]
    },
    {
      "clue": null,
      "answer": "southland",
      "answer_letters": "SOUTHLAND",
      "indices": [
        107,
        145,
        8,
        101,
        43,
        156,
        66,
        19,
        53
      ]
    },
    {
      "clue": null,
      "answer": "inputs",
      "answer_letters": "INPUTS",
      "indices": [
        119,
        115,
        72,
        93,
        42,
        158
      ]
    },
    {
      "clue": null,
      "answer": "newark",
      "answer_letters": "NEWARK",
      "indices": [
        150,
        161,
        40,
        172,
        7,
        37
      ]
    },
    {
      "clue": null,
      "answer": "awareness",
      "answer_letters": "AWARENESS",
      "indices": [
        5,
        118,
        18,
        33,
        48,
        9,
        152,
        132,
        49
      ]
    },
    {
      "clue": null,
      "answer": "triangle",
      "answer_letters": "TRIANGLE",
      "indices": [
        23,
        126,
        36,
        58,
        94,
        91,
        26,
        11
      ]
    },
    {
      "clue": null,
      "answer": "specialization",
      "answer_letters": "SPECIALIZATION",
      "indices": [
        170,
        146,
        141,
        155,
        113,
        111,
        124,
        78,
        79,
        102,
        120,
        163,
        139,
        31
      ]
    },
    {
      "clue": null,
      "answer": "earned",
      "answer_letters": "EARNED",
      "indices": [
        65,
        21,
        100,
        129,
        105,
        168
      ]
    },
    {
      "clue": null,
      "answer": "anthem",
      "answer_letters": "ANTHEM",
      "indices": [
        76,
        90,
        112,
        46,
        80,
        140
      ]
    }
  ],
  "chat": null
}