{
  "quote": "And what if you're trying to knock out another man,\"\" she said, sarcastic. There was no expression in his cool blue eyes. \"\"Then I kiss him,\"\" he said in the calmest of voices. \"\"Now you try it.",
  "quote_letters": "AND WHAT IF YOURE TRYING TO KNOCK OUT ANOTHER MAN SHE SAID SARCASTIC THERE WAS NO EXPRESSION IN HIS COOL BLUE EYES THEN I KISS HIM HE SAID IN THE CALMEST OF VOICES NOW YOU TRY IT",
  "source": "Anne Stuart, Cold As Ice",
  "source_letters": "ANNESTUARTCOLDASICE",
  "clues": [
    {
      "clue": null,
      "answer": "alison",
      "answer_letters": "ALISON",
      "indices": [
        47,
        106,
        89,
        151,
        30,
        22
      ]
    },
    {
      "clue": null,
      "answer": "noteworthy",
      "answer_letters": "NOTEWORTHY",
      "indices": [
        39,
        102,
        25,
        161,
        75,
        34,
        44,
        36,
        70,
        20
      ]
    },
    {
      "clue": null,
      "answer": "neighbourhoods",
      "answer_letters": "NEIGHBOURHOODS",
      "indices": [
        91,
        71,
        97,
        23,
        131,
        105,
        165,
        107,
        173,
        51,
        154,
        90,
        137,
        124
      ]
    },
    {
      "clue": null,
      "answer": "extension",
      "answer_letters": "EXTENSION",
      "indices": [
        43,
        83,
        115,
        73,
        48,
        59,
        120,
        80,
        140
      ]
    },
    {
      "clue": null,
      "answer": "shoots",
      "answer_letters": "SHOOTS",
      "indices": [
        54,
        116,
        26,
        13,
        65,
        77
      ]
    },
    {
      "clue": null,
      "answer": "thinks",
      "answer_letters": "THINKS",
      "indices": [
        41,
        5,
        56,
        79,
        28,
        88
      ]
    },
    {
      "clue": null,
      "answer": "utilities",
      "answer_letters": "UTILITIES",
      "indices": [
        35,
        7,
        123,
        148,
        136,
        142,
        66,
        112,
        125
      ]
    },
    {
      "clue": null,
      "answer": "awkward",
      "answer_letters": "AWKWARD",
      "indices": [
        6,
        4,
        122,
        166,
        38,
        85,
        57
      ]
    },
    {
      "clue": null,
      "answer": "rahman",
      "answer_letters": "RAHMAN",
      "indices": [
        61,
        63,
        96,
        46,
        147,
        118
      ]
    },
    {
      "clue": null,
      "answer": "theories",
      "answer_letters": "THEORIES",
      "indices": [
        177,
        143,
        110,
        169,
        19,
        21,
        150,
        64
      ]
    },
    {
      "clue": null,
      "answer": "cities",
      "answer_letters": "CITIES",
      "indices": [
        146,
        93,
        69,
        128,
        86,
        98
      ]
    },
    {
      "clue": null,
      "answer": "octave",
      "answer_letters": "OCTAVE",
      "indices": [
        101,
        67,
        152,
        55,
        157,
        144
      ]
    },
    {
      "clue": null,
      "answer": "lichen",
      "answer_letters": "LICHEN",
      "indices": [
        103,
        139,
        62,
        42,
        52,
        1
      ]
    },
    {
      "clue": null,
      "answer": "donkey",
      "answer_letters": "DONKEY",
      "indices": [
        2,
        158,
        94,
        32,
        117,
        168
      ]
    },
    {
      "clue": null,
      "answer": "amateurs",
      "answer_letters": "AMATEURS",
      "indices": [
        76,
        149,
        60,
        18,
        16,
        170,
        72,
        50
      ]
    },
    {
      "clue": null,
      "answer": "symphony",
      "answer_letters": "SYMPHONY",
      "indices": [
        87,
        12,
        129,
        84,
        127,
        40,
        164,
        111
      ]
    },
    {
      "clue": null,
      "answer": "issues",
      "answer_letters": "ISSUES",
      "indices": [
        159,
        162,
        134,
        14,
        82,
        113
      ]
    },
    {
      "clue": null,
      "answer": "certain",
      "answer_letters": "CERTAIN",
      "indices": [
        160,
        108,
        15,
        172,
        0,
        9,
        29
      ]
    },
    {
      "clue": null,
      "answer": "efficacy",
      "answer_letters": "EFFICACY",
      "indices": [
        132,
        10,
        155,
        176,
        31,
        135,
        100,
        174
      ]
    }
  ],
  "chat": null
}