{
  "quote": "She had so deep a kinship with the trees, so intuitive a sympathy with leaf and flower, that it seemed as if the blood in her veins was not slow-moving human blood, but volatile sap.",
  "quote_letters": "SHE HAD SO DEEP A KINSHIP WITH THE TREES SO INTUITIVE A SYMPATHY WITH LEAF AND FLOWER THAT IT SEEMED AS IF THE BLOOD IN HER VEINS WAS NOT SLOW-MOVING HUMAN BLOOD BUT VOLATILE SAP",
  "source": "Mary Webb, Gone to Earth",
  "source_letters": "MARYWEBBGONETOEARTH",
  "clues": [
    {
      "clue": null,
      "answer": "matthews",
      "answer_letters": "MATTHEWS",
      "indices": [
        143,
        169,
        136,
        46,
        120,
        98,
        130,
        41
      ]
    },
    {
      "clue": null,
      "answer": "appellate",
      "answer_letters": "APPELLATE",
      "indices": [
        153,
        14,
        177,
        13,
        139,
        70,
        176,
        31,
        173
      ]
    },
    {
      "clue": null,
      "answer": "revive",
      "answer_letters": "REVIVE",
      "indices": [
        84,
        96,
        51,
        66,
        166,
        121
      ]
    },
    {
      "clue": null,
      "answer": "yokohama",
      "answer_letters": "YOKOHAMA",
      "indices": [
        63,
        42,
        18,
        114,
        32,
        5,
        152,
        101
      ]
    },
    {
      "clue": null,
      "answer": "whitehead",
      "answer_letters": "WHITEHEAD",
      "indices": [
        82,
        150,
        91,
        92,
        33,
        108,
        12,
        60,
        6
      ]
    },
    {
      "clue": null,
      "answer": "events",
      "answer_letters": "EVENTS",
      "indices": [
        71,
        124,
        125,
        154,
        164,
        132
      ]
    },
    {
      "clue": null,
      "answer": "behind",
      "answer_letters": "BEHIND",
      "indices": [
        111,
        37,
        29,
        104,
        134,
        11
      ]
    },
    {
      "clue": null,
      "answer": "british",
      "answer_letters": "BRITISH",
      "indices": [
        156,
        122,
        50,
        28,
        44,
        8,
        68
      ]
    },
    {
      "clue": null,
      "answer": "gunshot",
      "answer_letters": "GUNSHOT",
      "indices": [
        148,
        151,
        147,
        21,
        4,
        81,
        86
      ]
    },
    {
      "clue": null,
      "answer": "offended",
      "answer_letters": "OFFENDED",
      "indices": [
        9,
        79,
        105,
        109,
        118,
        99,
        52,
        77
      ]
    },
    {
      "clue": null,
      "answer": "nationalist",
      "answer_letters": "NATIONALIST",
      "indices": [
        76,
        75,
        61,
        117,
        113,
        20,
        54,
        157,
        19,
        94,
        107
      ]
    },
    {
      "clue": null,
      "answer": "emission",
      "answer_letters": "EMISSION",
      "indices": [
        2,
        97,
        126,
        56,
        102,
        27,
        144,
        127
      ]
    },
    {
      "clue": null,
      "answer": "two-way",
      "answer_letters": "TWOWAY",
      "indices": [
        35,
        26,
        167,
        65,
        72,
        57
      ]
    },
    {
      "clue": null,
      "answer": "outlaw",
      "answer_letters": "OUTLAW",
      "indices": [
        135,
        163,
        89,
        168,
        131,
        141
      ]
    },
    {
      "clue": null,
      "answer": "establishments",
      "answer_letters": "ESTABLISHMENTS",
      "indices": [
        38,
        175,
        170,
        16,
        162,
        80,
        146,
        0,
        22,
        58,
        83,
        45,
        49,
        138
      ]
    },
    {
      "clue": null,
      "answer": "avoids",
      "answer_letters": "AVOIDS",
      "indices": [
        88,
        145,
        158,
        48,
        115,
        128
      ]
    },
    {
      "clue": null,
      "answer": "rudolf",
      "answer_letters": "RUDOLF",
      "indices": [
        36,
        47,
        160,
        140,
        172,
        73
      ]
    },
    {
      "clue": null,
      "answer": "tehsil",
      "answer_letters": "TEHSIL",
      "indices": [
        67,
        95,
        62,
        39,
        171,
        112
      ]
    },
    {
      "clue": null,
      "answer": "hip-hop",
      "answer_letters": "HIPHOP",
      "indices": [
        87,
        23,
        24,
        1,
        159,
        59
      ]
    }
  ],
  "chat": null
}