{
  "quote": "I also don't believe that whatever come after life depends on my correctly reciting a list of my transgressions-that sounds too much like an Erudite afterlife to me, all accuracy and no feeling.",
  "quote_letters": "I ALSO DONT BELIEVE THAT WHATEVER COME AFTER LIFE DEPENDS ON MY CORRECTLY RECITING A LIST OF MY TRANSGRESSIONS-THAT SOUNDS TOO MUCH LIKE AN ERUDITE AFTERLIFE TO ME ALL ACCURACY AND NO FEELING",
  "source": "Veronica Roth, Insurgent",
  "source_letters": "VERONICAROTHINSURGENT",
  "clues": [
    {
      "clue": null,
      "answer": "vehicles",
      "answer_letters": "VEHICLES",
      "indices": [
        17,
        103,
        26,
        0,
        169,
        14,
        42,
        87
      ]
    },
    {
      "clue": null,
      "answer": "earlier",
      "answer_letters": "EARLIER",
      "indices": [
        151,
        168,
        43,
        85,
        79,
        53,
        152
      ]
    },
    {
      "clue": null,
      "answer": "rudolf",
      "answer_letters": "RUDOLF",
      "indices": [
        67,
        171,
        50,
        58,
        3,
        40
      ]
    },
    {
      "clue": null,
      "answer": "offences",
      "answer_letters": "OFFENCES",
      "indices": [
        159,
        155,
        47,
        48,
        59,
        34,
        51,
        56
      ]
    },
    {
      "clue": null,
      "answer": "nascent",
      "answer_letters": "NASCENT",
      "indices": [
        99,
        22,
        121,
        170,
        18,
        80,
        78
      ]
    },
    {
      "clue": null,
      "answer": "inmate",
      "answer_letters": "INMATE",
      "indices": [
        188,
        119,
        61,
        2,
        70,
        185
      ]
    },
    {
      "clue": null,
      "answer": "conductors",
      "answer_letters": "CONDUCTORS",
      "indices": [
        76,
        90,
        178,
        143,
        128,
        64,
        150,
        107,
        74,
        100
      ]
    },
    {
      "clue": null,
      "answer": "attempted",
      "answer_letters": "ATTEMPTED",
      "indices": [
        173,
        158,
        123,
        16,
        36,
        52,
        114,
        162,
        120
      ]
    },
    {
      "clue": null,
      "answer": "rebounds",
      "answer_letters": "REBOUNDS",
      "indices": [
        32,
        37,
        12,
        124,
        142,
        54,
        7,
        4
      ]
    },
    {
      "clue": null,
      "answer": "offshore",
      "answer_letters": "OFFSHORE",
      "indices": [
        65,
        184,
        91,
        116,
        130,
        5,
        102,
        186
      ]
    },
    {
      "clue": null,
      "answer": "tomato",
      "answer_letters": "TOMATO",
      "indices": [
        111,
        35,
        161,
        113,
        41,
        125
      ]
    },
    {
      "clue": null,
      "answer": "holiday",
      "answer_letters": "HOLIDAY",
      "indices": [
        112,
        117,
        45,
        15,
        55,
        39,
        175
      ]
    },
    {
      "clue": null,
      "answer": "islamist",
      "answer_letters": "ISLAMIST",
      "indices": [
        154,
        105,
        165,
        177,
        93,
        133,
        109,
        23
      ]
    },
    {
      "clue": null,
      "answer": "nikolay",
      "answer_letters": "NIKOLAY",
      "indices": [
        181,
        86,
        134,
        8,
        71,
        27,
        62
      ]
    },
    {
      "clue": null,
      "answer": "stigma",
      "answer_letters": "STIGMA",
      "indices": [
        104,
        96,
        46,
        190,
        127,
        148
      ]
    },
    {
      "clue": null,
      "answer": "unicef",
      "answer_letters": "UNICEF",
      "indices": [
        118,
        9,
        77,
        129,
        31,
        149
      ]
    },
    {
      "clue": null,
      "answer": "record",
      "answer_letters": "RECORD",
      "indices": [
        141,
        13,
        69,
        182,
        66,
        179
      ]
    },
    {
      "clue": null,
      "answer": "glacial",
      "answer_letters": "GLACIAL",
      "indices": [
        101,
        187,
        83,
        174,
        106,
        164,
        166
      ]
    },
    {
      "clue": null,
      "answer": "eternal",
      "answer_letters": "ETERNAL",
      "indices": [
        29,
        145,
        140,
        97,
        189,
        98,
        153
      ]
    },
    {
      "clue": null,
      "answer": "negatively",
      "answer_letters": "NEGATIVELY",
      "indices": [
        138,
        68,
        81,
        137,
        10,
        144,
        30,
        146,
        132,
        94
      ]
    },
    {
      "clue": null,
      "answer": "twenty-three",
      "answer_letters": "TWENTYTHREE",
      "indices": [
        20,
        25,
        156,
        108,
        88,
        72,
        28,
        21,
        172,
        75,
        135
      ]
    }
  ],
  "chat": null
}