{
  "quote": "Why the congress, president, supreme court justices & government are all exempt from Obama care ? Basicly they are saying \"\"Do what I say and not what I do. Is that is a dictatorship ?",
  "quote_letters": "WHY THE CONGRESS PRESIDENT SUPREME COURT JUSTICES GOVERNMENT ARE ALL EXEMPT FROM OBAMA CARE BASICLY THEY ARE SAYING DO WHAT I SAY AND NOT WHAT I DO IS THAT IS A DICTATORSHIP ",
  "source": "\"\"Beta\"\" Metani' Marashi",
  "source_letters": "BETAMETANIMARASHI",
  "clues": [
    {
      "clue": null,
      "answer": "boyfriend",
      "answer_letters": "BOYFRIEND",
      "indices": [
        82,
        9,
        98,
        76,
        12,
        148,
        102,
        134,
        161
      ]
    },
    {
      "clue": null,
      "answer": "exploiting",
      "answer_letters": "EXPLOITING",
      "indices": [
        53,
        70,
        73,
        67,
        135,
        21,
        154,
        156,
        55,
        114
      ]
    },
    {
      "clue": null,
      "answer": "tolerate",
      "answer_letters": "TOLERATE",
      "indices": [
        164,
        78,
        97,
        69,
        30,
        83,
        136,
        63
      ]
    },
    {
      "clue": null,
      "answer": "astrophysics",
      "answer_letters": "ASTROPHYSICS",
      "indices": [
        110,
        126,
        25,
        54,
        117,
        172,
        139,
        2,
        48,
        162,
        8,
        15
      ]
    },
    {
      "clue": null,
      "answer": "medication",
      "answer_letters": "MEDICATION",
      "indices": [
        32,
        19,
        116,
        95,
        87,
        88,
        4,
        112,
        81,
        131
      ]
    },
    {
      "clue": null,
      "answer": "entering",
      "answer_letters": "ENTERING",
      "indices": [
        47,
        24,
        59,
        31,
        89,
        143,
        113,
        11
      ]
    },
    {
      "clue": null,
      "answer": "thoughts",
      "answer_letters": "THOUGHTS",
      "indices": [
        151,
        101,
        146,
        28,
        50,
        170,
        74,
        94
      ]
    },
    {
      "clue": null,
      "answer": "academies",
      "answer_letters": "ACADEMIES",
      "indices": [
        130,
        96,
        121,
        145,
        13,
        79,
        124,
        90,
        157
      ]
    },
    {
      "clue": null,
      "answer": "natasha",
      "answer_letters": "NATASHA",
      "indices": [
        10,
        65,
        166,
        159,
        149,
        120,
        165
      ]
    },
    {
      "clue": null,
      "answer": "ithaca",
      "answer_letters": "ITHACA",
      "indices": [
        45,
        141,
        1,
        61,
        46,
        93
      ]
    },
    {
      "clue": null,
      "answer": "mccarthy",
      "answer_letters": "MCCARTHY",
      "indices": [
        56,
        35,
        163,
        127,
        168,
        39,
        152,
        111
      ]
    },
    {
      "clue": null,
      "answer": "always",
      "answer_letters": "ALWAYS",
      "indices": [
        140,
        66,
        138,
        85,
        128,
        43
      ]
    },
    {
      "clue": null,
      "answer": "reserved",
      "answer_letters": "RESERVED",
      "indices": [
        38,
        33,
        27,
        71,
        77,
        52,
        6,
        132
      ]
    },
    {
      "clue": null,
      "answer": "adjustment",
      "answer_letters": "ADJUSTMENT",
      "indices": [
        105,
        22,
        41,
        42,
        169,
        44,
        84,
        107,
        58,
        122
      ]
    },
    {
      "clue": null,
      "answer": "subway",
      "answer_letters": "SUBWAY",
      "indices": [
        20,
        37,
        92,
        0,
        153,
        103
      ]
    },
    {
      "clue": null,
      "answer": "horsepower",
      "answer_letters": "HORSEPOWER",
      "indices": [
        5,
        167,
        106,
        14,
        23,
        29,
        36,
        119,
        57,
        62
      ]
    },
    {
      "clue": null,
      "answer": "imports",
      "answer_letters": "IMPORTS",
      "indices": [
        171,
        72,
        17,
        51,
        18,
        100,
        109
      ]
    }
  ],
  "chat": null
}