{
  "quote": "You just...you don't take crap from anyone. But not in the fake, rebellious way that most kids do it, like they got something to prove. You're real, and people respect you a lot for that.",
  "quote_letters": "YOU JUSTYOU DONT TAKE CRAP FROM ANYONE BUT NOT IN THE FAKE REBELLIOUS WAY THAT MOST KIDS DO IT LIKE THEY GOT SOMETHING TO PROVE YOURE REAL AND PEOPLE RESPECT YOU A LOT FOR THAT",
  "source": "Christina Daley, Radiant",
  "source_letters": "CHRISTINADALEYRADIANT",
  "clues": [
    {
      "clue": null,
      "answer": "compete",
      "answer_letters": "COMPETE",
      "indices": [
        155,
        90,
        111,
        25,
        98,
        77,
        148
      ]
    },
    {
      "clue": null,
      "answer": "hooker",
      "answer_letters": "HOOKER",
      "indices": [
        101,
        110,
        1,
        84,
        135,
        123
      ]
    },
    {
      "clue": null,
      "answer": "runoff",
      "answer_letters": "RUNOFF",
      "indices": [
        134,
        130,
        140,
        80,
        168,
        27
      ]
    },
    {
      "clue": null,
      "answer": "isolate",
      "answer_letters": "ISOLATE",
      "indices": [
        115,
        81,
        106,
        147,
        55,
        45,
        60
      ]
    },
    {
      "clue": null,
      "answer": "supply",
      "answer_letters": "SUPPLY",
      "indices": [
        68,
        40,
        153,
        146,
        63,
        158
      ]
    },
    {
      "clue": null,
      "answer": "ticket",
      "answer_letters": "TICKET",
      "indices": [
        172,
        65,
        22,
        56,
        154,
        166
      ]
    },
    {
      "clue": null,
      "answer": "italy's",
      "answer_letters": "ITALYS",
      "indices": [
        85,
        41,
        24,
        137,
        103,
        6
      ]
    },
    {
      "clue": null,
      "answer": "namesake",
      "answer_letters": "NAMESAKE",
      "indices": [
        48,
        71,
        30,
        144,
        87,
        136,
        97,
        52
      ]
    },
    {
      "clue": null,
      "answer": "astrology",
      "answer_letters": "ASTROLOGY",
      "indices": [
        76,
        152,
        107,
        59,
        169,
        164,
        159,
        105,
        8
      ]
    },
    {
      "clue": null,
      "answer": "dumont",
      "answer_letters": "DUMONT",
      "indices": [
        141,
        5,
        79,
        129,
        33,
        175
      ]
    },
    {
      "clue": null,
      "answer": "abbott",
      "answer_letters": "ABBOTT",
      "indices": [
        32,
        39,
        61,
        120,
        119,
        74
      ]
    },
    {
      "clue": null,
      "answer": "lookout",
      "answer_letters": "LOOKOUT",
      "indices": [
        64,
        9,
        44,
        19,
        124,
        2,
        17
      ]
    },
    {
      "clue": null,
      "answer": "enjoyed",
      "answer_letters": "ENJOYED",
      "indices": [
        37,
        116,
        4,
        165,
        34,
        132,
        12
      ]
    },
    {
      "clue": null,
      "answer": "yesterday",
      "answer_letters": "YESTERDAY",
      "indices": [
        128,
        151,
        109,
        93,
        20,
        28,
        89,
        174,
        72
      ]
    },
    {
      "clue": null,
      "answer": "rooftop",
      "answer_letters": "ROOFTOP",
      "indices": [
        150,
        35,
        13,
        54,
        7,
        29,
        143
      ]
    },
    {
      "clue": null,
      "answer": "avenge",
      "answer_letters": "AVENGE",
      "indices": [
        18,
        125,
        102,
        14,
        117,
        62
      ]
    },
    {
      "clue": null,
      "answer": "duluth",
      "answer_letters": "DULUTH",
      "indices": [
        86,
        67,
        95,
        10,
        113,
        173
      ]
    },
    {
      "clue": null,
      "answer": "iteration",
      "answer_letters": "ITERATION",
      "indices": [
        47,
        100,
        112,
        170,
        139,
        82,
        92,
        66,
        43
      ]
    },
    {
      "clue": null,
      "answer": "author",
      "answer_letters": "AUTHOR",
      "indices": [
        162,
        160,
        156,
        114,
        145,
        23
      ]
    },
    {
      "clue": null,
      "answer": "nephew",
      "answer_letters": "NEPHEW",
      "indices": [
        36,
        126,
        122,
        75,
        57,
        70
      ]
    },
    {
      "clue": null,
      "answer": "thirty",
      "answer_letters": "THIRTY",
      "indices": [
        15,
        51,
        96,
        131,
        50,
        0
      ]
    }
  ],
  "chat": "\"Rival in a sports competition\" \n\"Fisherman's equipment\" \n\"Drainage of excess water\" \n\"Set apart from others\" \n\"Provide with provisions\" \n\"Admittance pass\" \n\"Roman empire's moniker\" \n\"Study of celestial bodies\" \n\"Famous hotelier, Wilbur\" \n\"Surname of former Prime Minister\" \n\"Guard post for observation\" \n\"To take pleasure in\" \n\"Previous day\" \n\"Elevated outdoor area on a building\" \n\"To seek revenge\" \n\"Minnesota city on Lake Superior\" \n\"Repetition of a process\" \n\"Writer of a book\" \n\"Brother's son\" \n\"Number after twenty-nine\""
}