{
  "quote": "What kills a person at twenty-five? Leukemia. An accident. But George knows the better odds are that someone who passes at that age dies of unhappiness. Drug overdose. Suicide. Reckless behavior.",
  "quote_letters": "WHAT KILLS A PERSON AT TWENTY-FIVE LEUKEMIA AN ACCIDENT BUT GEORGE KNOWS THE BETTER ODDS ARE THAT SOMEONE WHO PASSES AT THAT AGE DIES OF UNHAPPINESS DRUG OVERDOSE SUICIDE RECKLESS BEHAVIOR",
  "source": "Scott Turow, Limitations",
  "source_letters": "SCOTTTUROWLIMITATIONS",
  "clues": [
    {
      "clue": "something worth betting on",
      "answer": "stakes",
      "answer_letters": "STAKES",
      "indices": [
        147,
        3,
        183,
        38,
        52,
        16
      ]
    },
    {
      "clue": "disputes that attract public attention",
      "answer": "controversies",
      "answer_letters": "CONTROVERSIES",
      "indices": [
        173,
        69,
        18,
        118,
        157,
        84,
        32,
        161,
        82,
        98,
        130,
        61,
        163
      ]
    },
    {
      "clue": "to be against something",
      "answer": "oppose",
      "answer_letters": "OPPOSE",
      "indices": [
        154,
        110,
        142,
        17,
        115,
        39
      ]
    },
    {
      "clue": "large vehicles used for transporting goods",
      "answer": "trucks",
      "answer_letters": "TRUCKS",
      "indices": [
        93,
        15,
        137,
        48,
        5,
        71
      ]
    },
    {
      "clue": "despite ",
      "answer": "though",
      "answer_letters": "THOUGH",
      "indices": [
        27,
        94,
        159,
        37,
        126,
        1
      ]
    },
    {
      "clue": "launches or pitches ",
      "answer": "throws",
      "answer_letters": "THROWS",
      "indices": [
        21,
        121,
        90,
        134,
        0,
        87
      ]
    },
    {
      "clue": "optimistic or cheerful",
      "answer": "upbeat",
      "answer_letters": "UPBEAT",
      "indices": [
        57,
        141,
        180,
        25,
        47,
        23
      ]
    },
    {
      "clue": "reversed or returned to an earlier state ",
      "answer": "reverted",
      "answer_letters": "REVERTED",
      "indices": [
        150,
        145,
        184,
        81,
        171,
        73,
        14,
        85
      ]
    },
    {
      "clue": "noticed or monitored ",
      "answer": "observed",
      "answer_letters": "OBSERVED",
      "indices": [
        102,
        56,
        132,
        65,
        63,
        155,
        36,
        168
      ]
    },
    {
      "clue": "areas of vulnerability or inadequacy ",
      "answer": "weaknesses",
      "answer_letters": "WEAKNESSES",
      "indices": [
        106,
        104,
        89,
        67,
        53,
        169,
        113,
        146,
        127,
        160
      ]
    },
    {
      "clue": "a company that specializes in aerospace and defense technology ",
      "answer": "lockheed",
      "answer_letters": "LOCKHEED",
      "indices": [
        7,
        62,
        166,
        174,
        182,
        181,
        91,
        51
      ]
    },
    {
      "clue": "contain as part of a whole",
      "answer": "include",
      "answer_letters": "INCLUDE",
      "indices": [
        6,
        26,
        49,
        35,
        164,
        158,
        156
      ]
    },
    {
      "clue": "a country in southeast africa",
      "answer": "malawi",
      "answer_letters": "MALAWI",
      "indices": [
        40,
        125,
        175,
        122,
        24,
        167
      ]
    },
    {
      "clue": "a hebrew prophet in the bible",
      "answer": "isaiah",
      "answer_letters": "ISAIAH",
      "indices": [
        143,
        177,
        11,
        165,
        42,
        107
      ]
    },
    {
      "clue": "a strong urge to do something, often something one knows is wrong ",
      "answer": "temptation",
      "answer_letters": "TEMPTATION",
      "indices": [
        96,
        114,
        100,
        13,
        123,
        20,
        79,
        185,
        108,
        68
      ]
    },
    {
      "clue": "possibly or open to debate ",
      "answer": "arguably",
      "answer_letters": "ARGUABLY",
      "indices": [
        117,
        187,
        60,
        151,
        44,
        77,
        8,
        28
      ]
    },
    {
      "clue": "relating to or characteristic of teenagers ",
      "answer": "teenage",
      "answer_letters": "TEENAGE",
      "indices": [
        80,
        75,
        101,
        103,
        2,
        64,
        176
      ]
    },
    {
      "clue": "a hebrew prophet in the bible",
      "answer": "isaiah",
      "answer_letters": "ISAIAH",
      "indices": [
        50,
        112,
        95,
        31,
        140,
        139
      ]
    },
    {
      "clue": "being upset or hurt by something ",
      "answer": "offended",
      "answer_letters": "OFFENDED",
      "indices": [
        186,
        30,
        135,
        172,
        138,
        86,
        78,
        129
      ]
    },
    {
      "clue": "periods of darkness ",
      "answer": "nights",
      "answer_letters": "NIGHTS",
      "indices": [
        45,
        41,
        152,
        74,
        120,
        9
      ]
    },
    {
      "clue": "owned and operated by the government",
      "answer": "state-owned",
      "answer_letters": "STATEOWNED",
      "indices": [
        178,
        54,
        111,
        58,
        131,
        99,
        70,
        144,
        33,
        149
      ]
    }
  ],
  "chat": "stakes - Something worth betting on\ncontroversies - Disputes that attract public attention\noppose - To be against something\ntrucks - Large vehicles used for transporting goods\nthough - Despite \nthrows - Launches or pitches \nupbeat - Optimistic or cheerful\nreverted - Reversed or returned to an earlier state \nobserved - Noticed or monitored \nweaknesses - Areas of vulnerability or inadequacy \nLockheed - A company that specializes in aerospace and defense technology \ninclude - Contain as part of a whole\nMalawi - A country in southeast Africa\nIsaiah - A Hebrew prophet in the Bible\ntemptation - A strong urge to do something, often something one knows is wrong \narguably - Possibly or open to debate \nteenage - Relating to or characteristic of teenagers \noffended - Being upset or hurt by something \nnights - Periods of darkness \nstate-owned - Owned and operated by the government"
}