{
  "quote": "You don't look so much like a great hero,' Jarrah said. 'I'm pretty sure I'm not,' Mack said wearily. 'My throat is hoarse from screaming in terror. I don't think heroes have that problem.",
  "quote_letters": "YOU DONT LOOK SO MUCH LIKE A GREAT HERO JARRAH SAID IM PRETTY SURE IM NOT MACK SAID WEARILY MY THROAT IS HOARSE FROM SCREAMING IN TERROR I DONT THINK HEROES HAVE THAT PROBLEM",
  "source": "Michael  Grant, The Call",
  "source_letters": "MICHAELGRANTTHECALL",
  "clues": [
    {
      "clue": null,
      "answer": "monitored",
      "answer_letters": "MONITORED",
      "indices": [
        74,
        1,
        147,
        23,
        144,
        106,
        135,
        172,
        4
      ]
    },
    {
      "clue": null,
      "answer": "imitation",
      "answer_letters": "IMITATION",
      "indices": [
        67,
        115,
        137,
        95,
        86,
        33,
        123,
        38,
        6
      ]
    },
    {
      "clue": null,
      "answer": "carried",
      "answer_letters": "CARRIED",
      "indices": [
        76,
        48,
        119,
        113,
        49,
        25,
        139
      ]
    },
    {
      "clue": null,
      "answer": "halfway",
      "answer_letters": "HALFWAY",
      "indices": [
        150,
        32,
        9,
        112,
        84,
        80,
        90
      ]
    },
    {
      "clue": null,
      "answer": "arturo",
      "answer_letters": "ARTURO",
      "indices": [
        75,
        108,
        100,
        18,
        37,
        169
      ]
    },
    {
      "clue": null,
      "answer": "enough",
      "answer_letters": "ENOUGH",
      "indices": [
        36,
        128,
        153,
        2,
        125,
        163
      ]
    },
    {
      "clue": null,
      "answer": "lakeside",
      "answer_letters": "LAKESIDE",
      "indices": [
        171,
        158,
        77,
        57,
        117,
        146,
        82,
        131
      ]
    },
    {
      "clue": null,
      "answer": "gather",
      "answer_letters": "GATHER",
      "indices": [
        29,
        44,
        142,
        145,
        110,
        133
      ]
    },
    {
      "clue": null,
      "answer": "remake",
      "answer_letters": "REMAKE",
      "indices": [
        152,
        160,
        17,
        99,
        24,
        154
      ]
    },
    {
      "clue": null,
      "answer": "adjective",
      "answer_letters": "ADJECTIVE",
      "indices": [
        107,
        50,
        40,
        65,
        19,
        162,
        102,
        159,
        120
      ]
    },
    {
      "clue": null,
      "answer": "north-south",
      "answer_letters": "NORTHSOUTH",
      "indices": [
        124,
        10,
        97,
        130,
        45,
        47,
        5,
        63,
        165,
        20
      ]
    },
    {
      "clue": null,
      "answer": "terror",
      "answer_letters": "TERROR",
      "indices": [
        59,
        85,
        43,
        132,
        15,
        168
      ]
    },
    {
      "clue": null,
      "answer": "thinks",
      "answer_letters": "THINKS",
      "indices": [
        7,
        157,
        52,
        141,
        12,
        109
      ]
    },
    {
      "clue": null,
      "answer": "horror",
      "answer_letters": "HORROR",
      "indices": [
        105,
        11,
        56,
        64,
        140,
        87
      ]
    },
    {
      "clue": null,
      "answer": "embassy",
      "answer_letters": "EMBASSY",
      "indices": [
        31,
        68,
        170,
        164,
        155,
        79,
        60
      ]
    },
    {
      "clue": null,
      "answer": "compositions",
      "answer_letters": "COMPOSITIONS",
      "indices": [
        118,
        114,
        173,
        55,
        134,
        103,
        81,
        72,
        88,
        71,
        70,
        62
      ]
    },
    {
      "clue": null,
      "answer": "artery",
      "answer_letters": "ARTERY",
      "indices": [
        121,
        30,
        58,
        151,
        42,
        0
      ]
    },
    {
      "clue": null,
      "answer": "lakshmi",
      "answer_letters": "LAKSHMI",
      "indices": [
        22,
        27,
        148,
        14,
        35,
        92,
        127
      ]
    },
    {
      "clue": null,
      "answer": "lymphoma",
      "answer_letters": "LYMPHOMA",
      "indices": [
        89,
        93,
        122,
        167,
        96,
        98,
        53,
        41
      ]
    }
  ],
  "chat": null
}