{
  "quote": "The president, just as any other American, deserves a legal defense against personal lawsuits not related to his office. But the costs of that defense should be borne by him and not the taxpayer.",
  "quote_letters": "THE PRESIDENT JUST AS ANY OTHER AMERICAN DESERVES A LEGAL DEFENSE AGAINST PERSONAL LAWSUITS NOT RELATED TO HIS OFFICE BUT THE COSTS OF THAT DEFENSE SHOULD BE BORNE BY HIM AND NOT THE TAXPAYER",
  "source": "Ben Nighthorse Campbell",
  "source_letters": "BENNIGHTHORSECAMPBELL",
  "clues": [
    {
      "clue": null,
      "answer": "barrow",
      "answer_letters": "BARROW",
      "indices": [
        155,
        80,
        30,
        160,
        93,
        85
      ]
    },
    {
      "clue": null,
      "answer": "enjoys",
      "answer_letters": "ENJOYS",
      "indices": [
        181,
        70,
        14,
        26,
        165,
        48
      ]
    },
    {
      "clue": null,
      "answer": "nathan",
      "answer_letters": "NATHAN",
      "indices": [
        92,
        171,
        179,
        1,
        22,
        175
      ]
    },
    {
      "clue": null,
      "answer": "needing",
      "answer_letters": "NEEDING",
      "indices": [
        144,
        75,
        53,
        102,
        8,
        23,
        54
      ]
    },
    {
      "clue": null,
      "answer": "issues",
      "answer_letters": "ISSUES",
      "indices": [
        108,
        130,
        90,
        15,
        162,
        16
      ]
    },
    {
      "clue": null,
      "answer": "goodbye",
      "answer_letters": "GOODBYE",
      "indices": [
        67,
        78,
        132,
        41,
        164,
        24,
        156
      ]
    },
    {
      "clue": null,
      "answer": "hottest",
      "answer_letters": "HOTTEST",
      "indices": [
        107,
        150,
        27,
        89,
        10,
        63,
        17
      ]
    },
    {
      "clue": null,
      "answer": "threatens",
      "answer_letters": "THREATENS",
      "indices": [
        122,
        180,
        35,
        146,
        68,
        135,
        44,
        79,
        7
      ]
    },
    {
      "clue": null,
      "answer": "husband",
      "answer_letters": "HUSBAND",
      "indices": [
        28,
        119,
        43,
        118,
        184,
        11,
        58
      ]
    },
    {
      "clue": null,
      "answer": "oliveira",
      "answer_letters": "OLIVEIRA",
      "indices": [
        159,
        83,
        168,
        46,
        6,
        88,
        190,
        99
      ]
    },
    {
      "clue": null,
      "answer": "rosenthal",
      "answer_letters": "ROSENTHAL",
      "indices": [
        5,
        111,
        71,
        47,
        39,
        138,
        123,
        84,
        52
      ]
    },
    {
      "clue": null,
      "answer": "suffix",
      "answer_letters": "SUFFIX",
      "indices": [
        148,
        151,
        60,
        112,
        114,
        185
      ]
    },
    {
      "clue": null,
      "answer": "effect",
      "answer_letters": "EFFECT",
      "indices": [
        42,
        142,
        133,
        143,
        37,
        104
      ]
    },
    {
      "clue": null,
      "answer": "clothes",
      "answer_letters": "CLOTHES",
      "indices": [
        126,
        98,
        176,
        12,
        136,
        101,
        86
      ]
    },
    {
      "clue": null,
      "answer": "appreciated",
      "answer_letters": "APPRECIATED",
      "indices": [
        66,
        4,
        186,
        45,
        59,
        115,
        69,
        38,
        100,
        29,
        153
      ]
    },
    {
      "clue": null,
      "answer": "matter",
      "answer_letters": "MATTER",
      "indices": [
        169,
        19,
        0,
        72,
        64,
        96
      ]
    },
    {
      "clue": null,
      "answer": "playhouse",
      "answer_letters": "PLAYHOUSE",
      "indices": [
        74,
        56,
        50,
        188,
        149,
        127,
        87,
        109,
        116
      ]
    },
    {
      "clue": null,
      "answer": "battista",
      "answer_letters": "BATTISTA",
      "indices": [
        158,
        32,
        177,
        94,
        36,
        128,
        129,
        137
      ]
    },
    {
      "clue": null,
      "answer": "endorsement",
      "answer_letters": "ENDORSEMENT",
      "indices": [
        61,
        172,
        173,
        105,
        76,
        77,
        189,
        33,
        124,
        161,
        120
      ]
    },
    {
      "clue": null,
      "answer": "leases",
      "answer_letters": "LEASES",
      "indices": [
        81,
        2,
        187,
        20,
        34,
        145
      ]
    },
    {
      "clue": null,
      "answer": "left-handed",
      "answer_letters": "LEFTHANDED",
      "indices": [
        152,
        97,
        113,
        183,
        167,
        55,
        62,
        140,
        141,
        9
      ]
    }
  ],
  "chat": null
}